fi/evals/__init__.py
fi/evals/evaluator.py
fi/evals/metrics/__init__.py
fi/evals/metrics/aggregated_metric.py
fi/evals/metrics/bleu.py
fi/evals/metrics/embedding_similarity.py
fi/evals/metrics/laveshtein.py
fi/evals/metrics/numeric_diff.py
fi/evals/metrics/rouge.py
fi/evals/metrics/semantic_list_contains.py
fi/evals/protect.py
fi/evals/templates.py
fi/evals/types.py
evals_ai-0.1.1.dist-info/METADATA
evals_ai-0.1.1.dist-info/WHEEL
evals_ai-0.1.1.dist-info/RECORD
