Metadata-Version: 2.3
Name: evals-ai
Version: 0.1.1
Summary: We help GenAI teams maintain high-accuracy for their Models in production.
Author: Future AGI
Author-email: no-reply@futureagi.com
Requires-Python: >3.9
Classifier: Programming Language :: Python :: 3
Classifier: Programming Language :: Python :: 3.10
Classifier: Programming Language :: Python :: 3.11
Classifier: Programming Language :: Python :: 3.12
Classifier: Programming Language :: Python :: 3.13
Requires-Dist: futureagi (>=0.6.2)
